[
  {
    "filename": "1744879071965_Avendus_MGD.pptx",
    "uploadedBy": "Unknown",
    "email": "Unknown",
    "timestamp": "2025-04-17T08:37:52.017Z"
  },
  {
    "filename": "1744881403483_Grant_Thornton_Bharat_Report.pdf",
    "uploadedBy": "Kathryn George",
    "email": "kathryn.george@saisonomni.com",
    "timestamp": "2025-04-17T09:16:43.733Z"
  },
  {
    "filename": "1744882093707_Assignment_1_Report_on_Colending_and_DA.docx",
    "uploadedBy": "Kathryn George",
    "email": "kathryn.george@saisonomni.com",
    "timestamp": "2025-04-17T09:28:13.739Z"
  },
  {
    "filename": "1744882573088_FY24_securitisation-bridging-a-funding-gap.pdf",
    "uploadedBy": "Kathryn George",
    "email": "kathryn.george@saisonomni.com",
    "timestamp": "2025-04-17T09:36:13.109Z"
  },
  {
    "filename": "1744882623385_Enterprise_FinTech-Report-2024_Chiratae_and_The_Digital_Fifth.pdf",
    "uploadedBy": "Kathryn George",
    "email": "kathryn.george@saisonomni.com",
    "timestamp": "2025-04-17T09:37:03.552Z"
  }
]